[{"id":802926095,"title":"Blog Template","order":1,"templateKey":"blog","customTemplate":false,"customTemplateFilename":null,"pageLinks":[],"dateCreated":"2025-01-22T21:33:34.211Z","dateUpdated":"2025-01-22T21:33:35.201Z","folderId":null,"pageName":"Blog Template","serverPageId":null,"sectionCount":1,"status":2,"backwardUrl":null},{"id":451913425,"title":"Post Template","order":2,"templateKey":"post","customTemplate":false,"customTemplateFilename":null,"pageLinks":[],"dateCreated":"2025-01-22T21:33:34.323Z","dateUpdated":"2025-01-22T21:33:35.202Z","folderId":null,"pageName":"Post Template","serverPageId":null,"sectionCount":1,"status":2,"backwardUrl":null},{"id":927928263,"title":"Product List Template","order":3,"templateKey":"products","customTemplate":false,"customTemplateFilename":null,"pageLinks":[],"dateCreated":"2025-01-22T21:33:34.448Z","dateUpdated":"2025-01-22T21:33:35.202Z","folderId":null,"pageName":"Product List Template","serverPageId":null,"sectionCount":1,"status":2,"backwardUrl":null},{"id":2049712255,"title":"Product Details Template","order":4,"templateKey":"product","customTemplate":false,"customTemplateFilename":null,"pageLinks":[],"dateCreated":"2025-01-22T21:33:34.543Z","dateUpdated":"2025-01-22T21:33:35.202Z","folderId":null,"pageName":"Product Details Template","serverPageId":null,"sectionCount":1,"status":2,"backwardUrl":null},{"id":91234206,"title":"Shopping Cart Template","order":5,"templateKey":"cart","customTemplate":false,"customTemplateFilename":null,"pageLinks":[],"dateCreated":"2025-01-22T21:33:34.619Z","dateUpdated":"2025-01-22T21:33:35.202Z","folderId":null,"pageName":"Shopping Cart Template","serverPageId":null,"sectionCount":1,"status":2,"backwardUrl":null},{"id":1003408322,"title":"Checkout Template","order":6,"templateKey":"checkout","customTemplate":false,"customTemplateFilename":null,"pageLinks":[],"dateCreated":"2025-01-22T21:33:34.719Z","dateUpdated":"2025-01-22T21:33:35.202Z","folderId":null,"pageName":"Checkout Template","serverPageId":null,"sectionCount":1,"status":2,"backwardUrl":null},{"id":125944994,"title":"Login Template","order":7,"templateKey":"login","customTemplate":false,"customTemplateFilename":null,"pageLinks":[],"dateCreated":"2025-01-22T21:33:34.780Z","dateUpdated":"2025-01-22T21:33:35.203Z","folderId":null,"pageName":"Login Template","serverPageId":null,"sectionCount":1,"status":2,"backwardUrl":null},{"id":845807244,"title":"Search Page Template","order":8,"templateKey":"Search","customTemplate":false,"customTemplateFilename":null,"pageLinks":[],"dateCreated":"2025-01-22T21:33:34.826Z","dateUpdated":"2025-01-22T21:33:35.203Z","folderId":null,"pageName":"Search Page Template","serverPageId":null,"sectionCount":1,"status":2,"backwardUrl":null},{"id":104968904,"title":"Page Password Template","order":9,"templateKey":"password","customTemplate":false,"customTemplateFilename":null,"pageLinks":[],"dateCreated":"2025-01-22T21:33:34.876Z","dateUpdated":"2025-01-22T21:33:35.203Z","folderId":null,"pageName":"Page Password Template","serverPageId":null,"sectionCount":1,"status":2,"backwardUrl":null},{"id":923713707,"title":"404 Not Found Template","order":10,"templateKey":"404","customTemplate":false,"customTemplateFilename":null,"pageLinks":[],"dateCreated":"2025-01-22T21:33:34.917Z","dateUpdated":"2025-01-22T21:33:35.203Z","folderId":null,"pageName":"404 Not Found Template","serverPageId":null,"sectionCount":1,"status":2,"backwardUrl":null},{"id":2767308169,"title":"Thank You Page Template","order":11,"templateKey":"ThankYou","customTemplate":false,"customTemplateFilename":null,"pageLinks":[],"dateCreated":"2025-01-22T21:33:34.954Z","dateUpdated":"2025-01-22T21:33:35.203Z","folderId":null,"pageName":"Thank You Page Template","serverPageId":null,"sectionCount":1,"status":2,"backwardUrl":null},{"id":95995826,"title":"О нас","order":100,"templateKey":null,"customTemplate":false,"customTemplateFilename":null,"pageLinks":[],"dateCreated":"2025-01-22T21:33:34.981Z","dateUpdated":"2025-01-22T21:45:01.567Z","folderId":null,"pageName":"О нас_95995826","serverPageId":null,"sectionCount":2,"status":2,"backwardUrl":null},{"id":254557123,"title":"Контакты","order":101,"templateKey":null,"customTemplate":false,"customTemplateFilename":null,"pageLinks":[],"dateCreated":"2025-01-22T21:33:35.005Z","dateUpdated":"2025-01-22T21:33:35.203Z","folderId":null,"pageName":"Контакты_254557123","serverPageId":null,"sectionCount":1,"status":2,"backwardUrl":null}]